dyna/__init__.py
dyna-1.0.dist-info/METADATA
dyna-1.0.dist-info/WHEEL
dyna-1.0.dist-info/top_level.txt
dyna-1.0.dist-info/RECORD
