Metadata-Version: 2.1
Name: dyna
Version: 1.0
Summary: Dyna is a domain-specific langauge for dynamic programming.
Author: Tim Vieira
